ternimator/__init__.py
ternimator/animations.py
ternimator/py.typed
ternimator-0.0.32.dist-info/WHEEL
ternimator-0.0.32.dist-info/entry_points.txt
ternimator-0.0.32.dist-info/METADATA
ternimator-0.0.32.dist-info/RECORD
