Metadata-Version: 2.4
Name: ternimator
Version: 0.0.32
Summary: Utitlities for terminal animations
Keywords: terminal animations,cli utility
Author: Huib Piguillet
Author-email: Huib Piguillet <huib@proton.me>
License-Expression: MIT
Classifier: Intended Audience :: Developers
Classifier: Topic :: Utilities
Classifier: Programming Language :: Python :: 3
Classifier: Programming Language :: Python :: 3.14
Classifier: Programming Language :: Python :: 3 :: Only
Requires-Dist: based-utils[keyboard]
Requires-Dist: kleur
Requires-Python: >=3.14
Project-URL: Github, https://github.com/githuib/ternimator
Project-URL: PyPI, https://pypi.org/project/ternimator/
